radicale_docecot_auth-0.2.dist-info/DESCRIPTION.rst
radicale_docecot_auth-0.2.dist-info/METADATA
radicale_docecot_auth-0.2.dist-info/RECORD
radicale_docecot_auth-0.2.dist-info/WHEEL
radicale_docecot_auth-0.2.dist-info/metadata.json
radicale_docecot_auth-0.2.dist-info/top_level.txt
radicale_dovecot_auth/__init__.py
radicale_dovecot_auth/dovecot_auth.py
